coreflow/__init__.py
coreflow/sat_funcs.py
coreflow/simulator.py
coreflow/analytics/__init__.py
coreflow/analytics/buckley_leverett.py
coreflow/analytics/interpret.py
coreflow/io/__init__.py
coreflow/io/math_tools.py
coreflow/io/plotting.py
coreflow/io/table_data.py
coreflow/simulators/__init__.py
coreflow/simulators/deck.py
coreflow/simulators/docker_client.py
coreflow/utils/__init__.py
coreflow/utils/general.py
coreflow/utils/os_utils.py
coreflow-0.0.1.dev3.dist-info/LICENSE
coreflow-0.0.1.dev3.dist-info/METADATA
coreflow-0.0.1.dev3.dist-info/WHEEL
coreflow-0.0.1.dev3.dist-info/top_level.txt
coreflow-0.0.1.dev3.dist-info/RECORD
