Metadata-Version: 2.1
Name: coreflow
Version: 0.0.1.dev3
Summary: Core flow and Special Core Analysis Interpretaion Tool.
Home-page: https://github.com/rmanasipov/coreflow
Author: Roman Manasipov, Bettina Jenei
Author-email: Roman Manasipov <romantheorphys@gmail.com>, Bettina Jenei <jeneibetti@gmail.com>
License: MIT License
Project-URL: repository, https://github.com/rmanasipov/coreflow
Classifier: Operating System :: OS Independent
Classifier: License :: OSI Approved :: MIT License
Classifier: Programming Language :: Python
Classifier: Programming Language :: Python :: 3
Requires-Python: >=3.8
License-File: LICENSE
Requires-Dist: pandas
Requires-Dist: openpyxl
Requires-Dist: scipy
Requires-Dist: plotly
Requires-Dist: bokeh
Requires-Dist: matplotlib
Requires-Dist: seaborn
Requires-Dist: docker
